Workbook

Sheet RTM
A1: ID | B1: Module | C1: Requirement | D1: Business requirement | E1: User role(s) | F1: Required screen | G1: Backend service | H1: Database entities | I1: API / Integration | J1: Workflow / Automation | K1: Security requirement | L1: Audit requirement | M1: AI requirement | N1: Priority | O1: Priority source | P1: Phase | Q1: Acceptance criteria | R1: Blueprint ref | S1: Open decisions
A2: PLT-001 | B2: Platform | C2: SSO sign-in via Microsoft Entra ID with MFA per Bank policy | D2: Only Bank-authenticated staff reach the platform | E2: All | F2: Sign-in, session expiry | G2: Identity & Access | H2: app_user | I2: Entra ID OIDC; /auth/* | J2: Session lifecycle; JIT user provisioning on first login | K2: MFA/conditional access enforced by IdP; token validation server-side; no local passwords in UAT/PROD | L2: Login success/failure, logout | M2: None | N2: P0 | O2: Derived | P2: 1 | Q2: User signs in with Entra; invalid/expired token returns 401; dev mock login impossible in UAT/PROD builds | R2: §5.1, §15, §16 | S2: DR-06, DR-48
A3: PLT-002 | B3: Platform | C3: Role + organisational scope resolved server-side on every request | D3: Users see only what role AND scope allow | E3: All | F3: All (role-adaptive navigation) | G3: Identity & Access (PolicyService) | H3: role, permission, role_permission, user_role_assignment, user_scope | I3: All endpoints via guard | J3: Scope recomputed on org change | K3: Deny-by-default; direct-URL/API calls re-checked; UI hiding never relied upon | L3: Permission denied events (security-relevant) | M3: None | N3: P0 | O3: BP §22 (admin story) | P3: 1 | Q3: Negative tests: cross-division, direct URL, API without UI all return 403 | R3: §5.1, §15 | S3: DR-06, DR-07
A4: PLT-003 | B4: Platform | C4: Admin manages roles and scopes with approval | D4: Controlled, reviewable access | E4: Platform Administrator, HR access approver | F4: Administration > Users & Access | G4: Identity & Access | H4: user_role_assignment, user_scope, approval | I4: /admin/users, /admin/role-assignments | J4: Maker-checker on grants; periodic access review export | K4: Admin cannot grant self; privileged roles need second approver | L4: Permission change (before/after) | M4: None | N4: P0 | O4: BP §22 | P4: 1 | Q4: Grant requires approval; audit shows who/when/what; self-grant rejected | R4: §15, §18, §22 | S4: DR-06, DR-44
A5: PLT-004 | B5: Platform | C5: Restricted field controls for salary, NID, passport | D5: Least privilege for high-risk personal data | E5: Document HR, ER (as approved) | F5: Masked fields across all screens | G5: EmployeeService + PolicyService | H5: permission (field-level) | I5: EmployeeService field projection | J5: Masked by default; reveal action where permitted | K5: Field-level permission; never in logs/notifications/exports unless permitted | L5: Restricted field reveal/read | M5: AI receives restricted field only if template requires it and user permitted | N5: P0 | O5: Derived | P5: 1 | Q5: User without field permission gets masked value from API (not just UI); logs contain no raw values | R5: §15, §25.1 | S5: DR-07
A6: PLT-005 | B6: Platform | C6: Role-adaptive navigation and permission-denied/empty/loading/error states | D6: One consistent platform UX | E6: All | F6: App shell, nav, state components | G6: Web app | H6: — | I6: /me (capabilities) | J6: — | K6: Navigation derived from server capabilities; backend still enforces | L6: — | M6: None | N6: P0 | O6: Derived | P6: 1 | Q6: Each role sees only authorised modules; denied direct URL shows permission-denied page and API 403 | R6: §3, §PROMPT 21 | S6: —
A7: PLT-006 | B7: Platform | C7: Separate DEV/UAT/PROD environments; DEV synthetic data only | D7: No real employee data outside PROD/approved UAT | E7: Platform team | F7: — | G7: Infra | H7: — | I7: — | J7: Seed scripts; masked-data process for UAT | K7: Repo scanning blocks real PII; UAT masked per approved process | L7: Deployment events | M7: None | N7: P0 | O7: Derived | P7: 1 | Q7: DEV seeded only from generator; CI secret/PII scan passes | R7: §15, §24 | S7: DR-45
A8: PLT-007 | B8: Platform | C8: Encryption in transit/at rest; secrets in Key Vault | D8: Bank security baseline | E8: Platform team | F8: — | G8: Infra | H8: — | I8: Key Vault, TLS | J8: Secret rotation | K8: TLS 1.2+; storage/DB encryption; no secrets in repo | L8: Secret access (platform logs) | M8: None | N8: P0 | O8: Derived | P8: 1 | Q8: Secret scan clean; app reads secrets only from vault/env | R8: §15, §16 | S8: DR-03
A9: PLT-008 | B9: Platform | C9: No public URLs for dashboards, attachments or documents | D9: Prevent link-sharing leakage | E9: All | F9: — | G9: DocumentService | H9: attachment | I9: Authorised streaming endpoint | J9: — | K9: All file access via authenticated, authorised API; no anonymous blob access | L9: File download | M9: None | N9: P0 | O9: Derived | P9: 1 | Q9: Blob container private; download without auth → 401; wrong scope → 403 | R9: §8.1, §15, §24 | S9: DR-39
A10: PLT-009 | B10: Platform | C10: Structured logging with PII redaction, error handling, observability | D10: Supportability without data leakage | E10: Platform team | F10: Error pages | G10: All | H10: — | I10: Application Insights / OpenTelemetry | J10: Alerting | K10: Log redaction of names/UID where not needed, salary, NID, passport, free text | L10: — | M10: None | N10: P0 | O10: BP §25.1 | P10: 1 | Q10: Log tests prove redaction; correlation ID on every request | R10: §16, §25.1 | S10: —
A11: PLT-010 | B11: Platform | C11: Feature flags per environment | D11: Safe incremental release | E11: Platform Administrator | F11: Administration > Feature flags | G11: ConfigurationService | H11: feature_flag | I11: /admin/feature-flags | J11: — | K11: Flag changes restricted and audited | L11: Flag change | M11: None | N11: P1 | O11: Assumed | P11: 1 | Q11: Disabled module routes return 404/403 server-side | R11: §4 | S11: —
A12: PLT-011 | B12: Platform | C12: Accessibility and responsive design (desktop first) | D12: Usable by all staff on Bank devices | E12: All | F12: All | G12: Web app | H12: — | I12: — | J12: — | K12: — | L12: — | M12: None | N12: P1 | O12: Assumed | P12: 1+ | Q12: Automated a11y checks pass on shell; keyboard navigation works | R12: §PROMPT 21 | S12: DR-40
... A117: OPS-002 | B117: Operations | C117: Production HRIS/Microsoft integrations, performance, mobile UX, BAU monitoring | D117: Scale and sustain | E117: IT, HR | F117: — | G117: All | H117: — | I117: HRIS, Graph | J117: — | K117: — | L117: — | M117: — | N117: P2 | O117: BP §21 Phase 10 | P117: 10 | Q117: Integration contract tests pass against UAT HRIS | R117: §21 | S117: DR-04

Sheet Summary
A1: RTM coverage by module and priority (formulas over RTM sheet)
A3: Module | B3: P0 | C3: P1 | D3: P2 | E3: Total
A4: Platform | B4: =COUNTIFS(RTM!$B$2:$B$117,$A4,RTM!$N$2:$N$117,"P0") -> 9 | C4: =COUNTIFS(RTM!$B$2:$B$117,$A4,RTM!$N$2:$N$117,"P1") -> 2 | D4: =COUNTIFS(RTM!$B$2:$B$117,$A4,RTM!$N$2:$N$117,"P2") -> 0 | E4: =SUM(B4:D4) -> 11
A5: EmployeeService | B5: =COUNTIFS(RTM!$B$2:$B$117,$A5,RTM!$N$2:$N$117,"P0") -> 3 | C5: =COUNTIFS(RTM!$B$2:$B$117,$A5,RTM!$N$2:$N$117,"P1") -> 0 | D5: =COUNTIFS(RTM!$B$2:$B$117,$A5,RTM!$N$2:$N$117,"P2") -> 0 | E5: =SUM(B5:D5) -> 3
A6: ConfigurationService | B6: =COUNTIFS(RTM!$B$2:$B$117,$A6,RTM!$N$2:$N$117,"P0") -> 3 | C6: =COUNTIFS(RTM!$B$2:$B$117,$A6,RTM!$N$2:$N$117,"P1") -> 0 | D6: =COUNTIFS(RTM!$B$2:$B$117,$A6,RTM!$N$2:$N$117,"P2") -> 0 | E6: =SUM(B6:D6) -> 3
A7: AuditService | B7: =COUNTIFS(RTM!$B$2:$B$117,$A7,RTM!$N$2:$N$117,"P0") -> 2 | C7: =COUNTIFS(RTM!$B$2:$B$117,$A7,RTM!$N$2:$N$117,"P1") -> 0 | D7: =COUNTIFS(RTM!$B$2:$B$117,$A7,RTM!$N$2:$N$117,"P2") -> 0 | E7: =SUM(B7:D7) -> 2
A8: NotificationService | B8: =COUNTIFS(RTM!$B$2:$B$117,$A8,RTM!$N$2:$N$117,"P0") -> 1 | C8: =COUNTIFS(RTM!$B$2:$B$117,$A8,RTM!$N$2:$N$117,"P1") -> 0 | D8: =COUNTIFS(RTM!$B$2:$B$117,$A8,RTM!$N$2:$N$117,"P2") -> 0 | E8: =SUM(B8:D8) -> 1
A9: DocumentService | B9: =COUNTIFS(RTM!$B$2:$B$117,$A9,RTM!$N$2:$N$117,"P0") -> 1 | C9: =COUNTIFS(RTM!$B$2:$B$117,$A9,RTM!$N$2:$N$117,"P1") -> 1 | D9: =COUNTIFS(RTM!$B$2:$B$117,$A9,RTM!$N$2:$N$117,"P2") -> 0 | E9: =SUM(B9:D9) -> 2
A10: Reporting | B10: =COUNTIFS(RTM!$B$2:$B$117,$A10,RTM!$N$2:$N$117,"P0") -> 0 | C10: =COUNTIFS(RTM!$B$2:$B$117,$A10,RTM!$N$2:$N$117,"P1") -> 1 | D10: =COUNTIFS(RTM!$B$2:$B$117,$A10,RTM!$N$2:$N$117,"P2") -> 0 | E10: =SUM(B10:D10) -> 1
A11: HR Action Centre | B11: =COUNTIFS(RTM!$B$2:$B$117,$A11,RTM!$N$2:$N$117,"P0") -> 8 | C11: =COUNTIFS(RTM!$B$2:$B$117,$A11,RTM!$N$2:$N$117,"P1") -> 1 | D11: =COUNTIFS(RTM!$B$2:$B$117,$A11,RTM!$N$2:$N$117,"P2") -> 0 | E11: =SUM(B11:D11) -> 9
A12: People Analytics | B12: =COUNTIFS(RTM!$B$2:$B$117,$A12,RTM!$N$2:$N$117,"P0") -> 14 | C12: =COUNTIFS(RTM!$B$2:$B$117,$A12,RTM!$N$2:$N$117,"P1") -> 2 | D12: =COUNTIFS(RTM!$B$2:$B$117,$A12,RTM!$N$2:$N$117,"P2") -> 3 | E12: =SUM(B12:D12) -> 19
A13: Engagement | B13: =COUNTIFS(RTM!$B$2:$B$117,$A13,RTM!$N$2:$N$117,"P0") -> 0 | C13: =COUNTIFS(RTM!$B$2:$B$117,$A13,RTM!$N$2:$N$117,"P1") -> 11 | D13: =COUNTIFS(RTM!$B$2:$B$117,$A13,RTM!$N$2:$N$117,"P2") -> 0 | E13: =SUM(B13:D13) -> 11
A14: Fun with Teams | B14: =COUNTIFS(RTM!$B$2:$B$117,$A14,RTM!$N$2:$N$117,"P0") -> 0 | C14: =COUNTIFS(RTM!$B$2:$B$117,$A14,RTM!$N$2:$N$117,"P1") -> 6 | D14: =COUNTIFS(RTM!$B$2:$B$117,$A14,RTM!$N$2:$N$117,"P2") -> 0 | E14: =SUM(B14:D14) -> 6
A15: ER Case Management | B15: =COUNTIFS(RTM!$B$2:$B$117,$A15,RTM!$N$2:$N$117,"P0") -> 8 | C15: =COUNTIFS(RTM!$B$2:$B$117,$A15,RTM!$N$2:$N$117,"P1") -> 6 | D15: =COUNTIFS(RTM!$B$2:$B$117,$A15,RTM!$N$2:$N$117,"P2") -> 0 | E15: =SUM(B15:D15) -> 14
... A22: Operations | B22: =COUNTIFS(RTM!$B$2:$B$117,$A22,RTM!$N$2:$N$117,"P0") -> 1 | C22: =COUNTIFS(RTM!$B$2:$B$117,$A22,RTM!$N$2:$N$117,"P1") -> 0 | D22: =COUNTIFS(RTM!$B$2:$B$117,$A22,RTM!$N$2:$N$117,"P2") -> 1 | E22: =SUM(B22:D22) -> 2
A23: Total | B23: =SUM(B4:B22) -> 66 | C23: =SUM(C4:C22) -> 44 | D23: =SUM(D4:D22) -> 6 | E23: =SUM(E4:E22) -> 116
A25: Check: rows in RTM | B25: =COUNTA(RTM!$A$2:$A$117) -> 116

Sheet Legend
A1: Priority source | B1: BP §22 = stated in blueprint backlog; Derived = required to deliver a BP §22 story or blueprint control; Assumed = build-team proposal awaiting confirmation
A2: Phase | B2: Blueprint §21 phase numbers. '4b (proposed)' = resequencing proposal DR-43, not yet approved
A3: Open decisions | B3: DR-xx items in docs/00-planning/L-decisions-register.md
A4: Source of truth | B4: Edit docs/requirements/rtm_data.py then run build_rtm.py; do not edit this workbook directly
